arm_converter/__init__.py
arm_converter/__main__.py
arm_converter/tools/aarch64-none-elf-as.exe
arm_converter/tools/aarch64-none-elf-objdump.exe
arm_converter/tools/arm-none-eabi-as.exe
arm_converter/tools/arm-none-eabi-objdump.exe
arm_converter-0.1.0.dist-info/LICENSE
arm_converter-0.1.0.dist-info/METADATA
arm_converter-0.1.0.dist-info/WHEEL
arm_converter-0.1.0.dist-info/top_level.txt
arm_converter-0.1.0.dist-info/RECORD
