Metadata-Version: 2.1
Name: arm-converter
Version: 0.1.0
Summary: Convert ARM instructions to machine code
Author-email: Yiheng Quan <development.henryquan@gmail.com>
Project-URL: Homepage, https://github.com/HenryQuan/ARM-Converter
Keywords: arm,converter,ios
Classifier: Programming Language :: Python :: 3
Classifier: License :: OSI Approved :: GNU Affero General Public License v3
Classifier: Operating System :: Microsoft :: Windows
Classifier: Topic :: Utilities
Requires-Python: >=3.6
License-File: LICENSE
